sparkonda
