Metadata-Version: 1.1
Name: sparkonda
Version: 0.2.2
Summary: Minimalistic utility library to manage conda environments for pyspark jobs on yarn clusters
Home-page: https://github.com/moutai/sparkonda
Author: Moussa Taifi
Author-email: @moutai
License: ISCL
Keywords: sparkonda
Platform: UNKNOWN
Classifier: Development Status :: 2 - Pre-Alpha
Classifier: Intended Audience :: Developers
Classifier: License :: OSI Approved :: ISC License (ISCL)
Classifier: Natural Language :: English
Classifier: Programming Language :: Python :: 2.7
